docs/__init__.py
prep/__init__.py
prep/analyze_britanova.py
prep/analyze_emerson.py
prep/assemble_britanova.py
prep/assemble_emerson.py
prep/assemble_ravens.py
prep/assemble_ruggiero.py
prep/assemble_wirasinha.py
tcrsampler/__init__.py
tcrsampler/sampler.py
tcrsampler/setup_db.py
tcrsampler/trial.py
tcrsampler/db/__init__.py
tcrsampler/db/alphabeta_db.tsv
tcrsampler/db/gammadelta_db.tsv
tcrsampler/tests/__init__.py
tcrsampler/tests/pmbc_mixcr_example_data.txt
tcrsampler/tests/test_sampler.py
tcrsampler/tests/test_setup_db.py
tcrsampler-0.1.9.dist-info/LICENSE
tcrsampler-0.1.9.dist-info/METADATA
tcrsampler-0.1.9.dist-info/WHEEL
tcrsampler-0.1.9.dist-info/top_level.txt
tcrsampler-0.1.9.dist-info/RECORD
