Metadata-Version: 2.1
Name: tcrsampler
Version: 0.1.9
Summary: Sample TCRs according to VJ gene usage frequency
Home-page: https://github.com/kmayerb/tcrsampler
Author: Koshlan Mayer-Blackwell
Author-email: kmayerbl@fredhutch.org
Maintainer: Koshlan Mayer-Blackwell
Maintainer-email: kmayerbl@fredhutch.org
License: MIT
Platform: UNKNOWN
Requires-Dist: numpy (>=1.18.1)
Requires-Dist: pandas (>=0.24.2)
Requires-Dist: progress (>=1.5)
